{
	"credit": "Made with Blockbench",
	"textures": {
		"0": "drk:item/rottenheart",
		"particle": "drk:item/rottenheart"
	},
	"elements": [
		{
			"from": [6, 1, 7],
			"to": [10, 5, 10],
			"rotation": {"angle": 0, "axis": "y", "origin": [8, 3.25, 8.5]},
			"faces": {
				"north": {"uv": [0, 0, 4, 4], "texture": "#0"},
				"east": {"uv": [4, 0, 7, 4], "texture": "#0"},
				"south": {"uv": [0, 4, 4, 8], "texture": "#0"},
				"west": {"uv": [4, 4, 7, 8], "texture": "#0"},
				"up": {"uv": [11, 3, 7, 0], "texture": "#0"},
				"down": {"uv": [11, 3, 7, 6], "texture": "#0"}
			}
		},
		{
			"from": [7, 0, 8],
			"to": [9, 1, 9],
			"rotation": {"angle": 0, "axis": "y", "origin": [8, 3.25, 8.5]},
			"faces": {
				"north": {"uv": [7, 6, 9, 7], "texture": "#0"},
				"east": {"uv": [8, 8, 9, 9], "texture": "#0"},
				"south": {"uv": [7, 7, 9, 8], "texture": "#0"},
				"west": {"uv": [0, 9, 1, 10], "texture": "#0"},
				"up": {"uv": [2, 9, 0, 8], "texture": "#0"},
				"down": {"uv": [4, 8, 2, 9], "texture": "#0"}
			}
		},
		{
			"from": [8.5, 5, 8],
			"to": [9.5, 6, 9],
			"rotation": {"angle": 0, "axis": "y", "origin": [8, 3.25, 8.5]},
			"faces": {
				"north": {"uv": [1, 9, 2, 10], "texture": "#0"},
				"east": {"uv": [2, 9, 3, 10], "texture": "#0"},
				"south": {"uv": [3, 9, 4, 10], "texture": "#0"},
				"west": {"uv": [9, 6, 10, 7], "texture": "#0"},
				"up": {"uv": [10, 8, 9, 7], "texture": "#0"},
				"down": {"uv": [9, 9, 8, 10], "texture": "#0"}
			}
		},
		{
			"from": [6.5, 5, 8],
			"to": [7.5, 7, 9],
			"rotation": {"angle": 0, "axis": "y", "origin": [8, 3.25, 8.5]},
			"faces": {
				"north": {"uv": [4, 8, 5, 10], "texture": "#0"},
				"east": {"uv": [5, 8, 6, 10], "texture": "#0"},
				"south": {"uv": [6, 8, 7, 10], "texture": "#0"},
				"west": {"uv": [7, 8, 8, 10], "texture": "#0"},
				"up": {"uv": [10, 9, 9, 8], "texture": "#0"},
				"down": {"uv": [10, 9, 9, 10], "texture": "#0"}
			}
		}
	],
	"display": {
		"thirdperson_righthand": {
			"rotation": [34.25, 0, 0],
			"translation": [0, 4.75, 2]
		},
		"thirdperson_lefthand": {
			"rotation": [34.25, 0, 0],
			"translation": [0, 4.75, 2]
		},
		"firstperson_righthand": {
			"rotation": [-157.94, 73.87, 158.7],
			"translation": [-1.25, 9.75, 2.5]
		},
		"firstperson_lefthand": {
			"rotation": [-157.94, 73.87, 158.7],
			"translation": [-0.25, 9.75, 2.5]
		},
		"ground": {
			"rotation": [176.9, 59.93, -177.28],
			"translation": [0.5, 4.75, 0]
		},
		"gui": {
			"rotation": [36.06, -30.04, 18.43],
			"translation": [-2, 6.75, -2],
			"scale": [1.72266, 1.46094, 1]
		},
		"head": {
			"rotation": [-0.48, -0.27, 0.31],
			"translation": [0, 9.25, -2],
			"scale": [3.13672, 1, 3.75391]
		},
		"fixed": {
			"rotation": [8, -23.66, 22.56],
			"translation": [-1.5, 4.75, -2]
		}
	},
	"groups": [
		{
			"name": "rottenheart",
			"origin": [8, 8, 8],
			"color": 0,
			"children": [0, 1, 2, 3]
		}
	]
}